openqasm_sphinx/VERSION.txt
openqasm_sphinx/__init__.py
openqasm_sphinx/_version.py
openqasm_sphinx/domain.py
openqasm_sphinx-0.1.0.dist-info/LICENSE
openqasm_sphinx-0.1.0.dist-info/METADATA
openqasm_sphinx-0.1.0.dist-info/WHEEL
openqasm_sphinx-0.1.0.dist-info/top_level.txt
openqasm_sphinx-0.1.0.dist-info/RECORD
