Metadata-Version: 2.1
Name: openqasm-sphinx
Version: 0.1.0
Summary: Sphinx tools for OpenQASM programs
Author: OpenQASM contributors
License: Apache 2.0
Keywords: openqasm,quantum programming language,documentation,Sphinx
Classifier: Environment :: Console
Classifier: Intended Audience :: Developers
Classifier: Intended Audience :: Science/Research
Classifier: License :: OSI Approved :: Apache Software License
Classifier: Programming Language :: Python :: 3 :: Only
Classifier: Topic :: Scientific/Engineering
Requires-Python: >=3.8
License-File: LICENSE
